pysparql_anything/__about__.py
pysparql_anything/__init__.py
pysparql_anything/args_handlers.py
pysparql_anything/cli.py
pysparql_anything/executor.py
pysparql_anything/sparql_anything.py
pysparql_anything/sparql_anything_reflection.py
pysparql_anything/utilities.py
pysparql_anything-1.0.0.0.dist-info/METADATA
pysparql_anything-1.0.0.0.dist-info/WHEEL
pysparql_anything-1.0.0.0.dist-info/entry_points.txt
pysparql_anything-1.0.0.0.dist-info/licenses/LICENSE
pysparql_anything-1.0.0.0.dist-info/RECORD
