Metadata-Version: 2.4
Name: pysparql_anything
Version: 1.0.0.0
Summary: The SPARQL Anything Python library.
Project-URL: Documentation, https://github.com/SPARQL-Anything/PySPARQL-Anything/blob/main/README.md
Project-URL: Issues, https://github.com/SPARQL-Anything/PySPARQL-Anything/issues
Project-URL: Source, https://github.com/SPARQL-Anything/PySPARQL-Anything
Author-email: Marco Ratta <marco.ratta1@open.ac.uk>, Enrico Daga <enrico.daga@open.ac.uk>
License-Expression: Apache-2.0
License-File: LICENSE
Keywords: RDF,SPARQL,knowledge graphs,linked data,networkx,rdflib,sematic web
Classifier: Development Status :: 5 - Production/Stable
Classifier: License :: OSI Approved :: Apache Software License
Classifier: Operating System :: OS Independent
Classifier: Programming Language :: Python :: 3.9
Classifier: Programming Language :: Python :: 3.10
Classifier: Programming Language :: Python :: 3.11
Classifier: Programming Language :: Python :: Implementation :: CPython
Classifier: Programming Language :: Python :: Implementation :: PyPy
Requires-Python: >=3.9
Requires-Dist: networkx==3.*
Requires-Dist: pandas==2.*
Requires-Dist: pygithub==2.*
Requires-Dist: pyjnius==1.*
Requires-Dist: rdflib==7.*
Requires-Dist: requests==2.*
Requires-Dist: tqdm==4.*
